Workbook

Sheet Como preencher
A1: Mini-gabarito: 70 questões
A3: Objetivo | B3: Dizer, com o SEU julgamento, em que tema cada questão deveria ficar. Depois comparamos com o que o modelo respondeu para medir a precisão.
A4: Regra de ouro | B4: NÃO olhe nenhum resultado do modelo antes de terminar. Se olhar, o gabarito deixa de ser independente e a medida perde valor.
A5: Células amarelas | B5: São as únicas que você edita. Cinza = texto da questão e resultado automático (não edite).
A6: tema_id | B6: Número do tema central (aba 'Temas'; use Ctrl+F no caminho). Escolha a lista suspensa ou digite o número. A coluna 'Caminho' mostra o nome para você conferir.
A7: Subtema ou tema pai? | B7: Se a questão claramente trata de um subtema, use o subtema. Se cobre vários subtemas do mesmo tema, ou você hesita entre irmãos, use o tema pai e marque certeza 'media'.
A8: tema_alternativo_id | B8: Só se estiver em dúvida entre dois temas de verdade: o 2º candidato mais provável. Pode ficar vazio.
A9: extras_ids | B9: Outros temas que a questão também cobre, separados por ';' (ex.: 4708;5157). Pode ficar vazio.
A10: certeza | B10: alta = você apostaria; media = tem uma boa hipótese; baixa = chute ou questão ambígua. Seja honesto: essa coluna vira análise no relatório.
A11: fora | B11: Escreva 'sim' se NENHUM tema da lista serve (ex.: matéria de Direito Constitucional). Nesse caso deixe tema_id vazio.
A12: Temas gêmeos | B12: Os nós com tema_id a partir de 6716 foram retirados da lista (duplicatas vazias). Ex.: para Lei Maria da Penha, use 4704, não 6724. Veja gemeos.csv.
A13: Tempo | B13: Calcule uns 2 a 3 minutos por questão (cerca de 2 a 3 horas no total). Pode salvar e continuar depois.
A14: Ao terminar | B14: Salve o arquivo e guarde uma cópia em data/amostra_rotulada.xlsx. Não altere os IDs nem a ordem das linhas.
A16: Exemplo de linha preenchida (não faz parte da amostra)
A17: Campo | B17: Valor de exemplo
A18: id | B18: Q9999
A19: tema_id | B19: 4704
A20: tema_alternativo_id | B20: (vazio)
A21: extras_ids | B21: 4708
A22: certeza | B22: alta
A23: fora | B23: (vazio)
A24: observação | B24: Violência doméstica com tráfico como tema secundário
A25: Amostra: 70 questões sorteadas de 359 com semente 42 (random_state). Ordenadas por ID.

Sheet Rotulagem
A1: id | B1: Questão (enunciado + comando) | C1: Alternativas | D1: tema_id | E1: Caminho (confira) | F1: tema_alternativo_id | G1: extras_ids | H1: certeza | I1: fora | J1: observação
A2: Q0004 | B2: Sobre jurisdição e competência no processo penal, analise as assertivas e assinale a alternativa correta: I – Caso um prefeito municipal cometa crimes contra bens da União, ele somente poderá ser processado criminalmente mediante ação penal instaurada no tribunal de justiça do respectivo estado. II – Compete ao Tribunal Regional Federal processar e julgar prefeito municipal acusado de crime federal vale dizer, crime praticado pelo prefeito em detrimento de bens, serviços ou interesses da União Federal, empresas públicas e autarquias federais. III - Não sendo conhecido o lugar da infração penal, a competência regular-se-á pelo domicílio ou residência do réu. IV - O foro competente para processar e julgar os prefeitos municipais é o tribunal de justiça estadual. V - Prevalece o foro por prerrogativa de função, ainda que a ação judicial seja iniciada após a cessação do mandato eletivo do prefeito municipal. COMANDO: Assinale a alternativa correta. | C2: A) Apenas as assertivas II, III e IV são verdadeiras. B) Apenas as assertivas I, II e III são verdadeiras. C) Apenas as assertivas I, II e IV são verdadeiras. D) Apenas as assertivas II, IV e V são verdadeiras. E) Apenas as alternativas II, III e V são verdadeiras. | E2: =IF(D2="","",IFERROR(INDEX(Temas!$C$2:$C$352,MATCH(D2,Temas!$A$2:$A$352,0)),"ID NÃO ENCONTRADO"))
A3: Q0006 | B3: Sobre os crimes de furto e roubo, analise as afirmativas a seguir. I. De acordo com a teoria da contrectatio, a consumação do crime de furto ocorre quando há o contato físico com a coisa alheia móvel, desde que haja a inversão da posse. II. Há delito de furto e não de roubo quando o sujeito ativo se vale de narcóticos para reduzir a vítima à impossibilidade de resistência para se apoderar dos pertences dela. III. Não é cabível tentativa de roubo impróprio. COMANDO: Está correto o que se afirma em | C3: A) III, apenas. B) I e II, apenas. C) I e III, apenas. D) II e III, apenas. E) I, II e III. | E3: =IF(D3="","",IFERROR(INDEX(Temas!$C$2:$C$352,MATCH(D3,Temas!$A$2:$A$352,0)),"ID NÃO ENCONTRADO"))
A4: Q0010 | B4: Com relação aos crimes contra o meio ambiente, assinale a opção correta, conforme entendimento do STJ e do STF. COMANDO: Assinale a opção correta, conforme entendimento do STJ e do STF. | C4: A) Considere que Gil, a fim de comemorar, durante a madrugada, em zona urbana, a vitória de determinado time de futebol, tenha ajustado o aparelho de som do veículo em volume muito acima do limite permitido na legislação local, perturbando o sono e o sossego da vizinhança, e que esta tenha acionado o órgão municipal responsável. Considere, ainda, que o referido aparelho de som tenha sido apreendido, e Gil, conduzido à delegacia de polícia. Nessa situação, a conduta de Gil é atípica, visto que a poluição sonora não está expressamente prevista na lei de crimes ambientais. B) O crime ambiental que consiste em impedir o nascimento de nova vegetação ou dificultar a regeneração natural de florestas e demais formas de vegetação é crime permanente, visto que a consumação do delito se protrai no tempo, violando o bem jurídico tutelado de forma contínua e duradoura, renovando-se, a cada momento a consumação, consoante entendimento do STF. C) Em se tratando dos crimes contra o meio ambiente, admite-se responsabilização penal unicamente da pessoa jurídica, salvo se a imputação for pela prática de delitos culposos. D) Os tribunais superiores, no que concerne aos crimes ambientais, rejeitam a incidência do sistema da dupla imputação ou sistema da imputação paralela dada a ocorrência de bis in idem na responsabilização, pelo mesmo crime, de mais de uma pessoa. E) O crime de deixar de cumprir obrigação de relevante interesse ambiental, previsto no rol dos crimes contra a administração pública ambiental, é crime omissivo próprio, punido apenas na forma dolosa, e se caracteriza quando o agente público deixa de praticar o ato, contrariando o dever legal de fazê-lo para evitar o resultado lesivo ao meio ambiente, consoante entendimento do STJ. | E4: =IF(D4="","",IFERROR(INDEX(Temas!$C$2:$C$352,MATCH(D4,Temas!$A$2:$A$352,0)),"ID NÃO ENCONTRADO"))
A5: Q0016 | B5: À luz da atual jurisprudência dos Tribunais Superiores sobre o tema prisão, avalie as assertivas a seguir. I. Consoante a jurisprudência do Superior Tribunal de Justiça, em razão da Lei nº 13.964/2019, não é mais possível ao Juiz, de ofício, decretar ou converter a prisão em flagrante em prisão preventiva. II. De acordo com o entendimento do Supremo Tribunal Federal, é incompatível com a Constituição Federal – por ofensa ao princípio da isonomia (Art. 3º, inciso IV; e Art. 5º, caput, da CRFB/88) – a previsão contida no inciso VII do Art. 295 do CPP que concede o direito à prisão especial, até decisão penal definitiva, a pessoas com diploma de ensino superior. III. O Supremo Tribunal Federal atribuiu interpretação conforme a Constituição Federal, ao § 1º do Art. 3º-B do CPP, incluído pela Lei nº 13.964/2019, para estabelecer que o preso em flagrante ou por força de mandado de prisão provisória será sempre encaminhado à presença do Juiz das Garantias, no prazo de 72 horas. Está correto o que se afirma em | C5: A) I, apenas. B) II, apenas. C) I e II, apenas. D) II e III, apenas. E) I e III, apenas. | E5: =IF(D5="","",IFERROR(INDEX(Temas!$C$2:$C$352,MATCH(D5,Temas!$A$2:$A$352,0)),"ID NÃO ENCONTRADO"))
A6: Q0023 | B6: Sobre o Tribunal do Júri, é INCORRETO afirmar: | C6: A) Seu procedimento desdobra-se em juízo da acusação, que analisa a admissibilidade da pretensão punitiva, e juízo da causa, que diz respeito ao mérito da acusação. B) Se o acusado houver permanecido preso durante a instrução criminal, a pronúncia do juiz importará em automática manutenção da cautela extrema, sendo, por outro lado, necessária a motivação do decreto de prisão na hipótese de o pronunciado encontrar-se solto. C) A decisão de impronúncia não faz coisa julgada formal e material. D) Se o advogado do acusado, regularmente intimado, não comparecer à sessão de julgamento, e não houver escusa legítima, o julgamento será adiado uma única vez, cabendo ao juiz-presidente intimar a Defensoria Pública para o novo julgamento. E) Nos termos da lei, o sistema de colheita de depoimentos em plenário é, para as partes, o do exame direto e cruzado, ao passo que, para os jurados, o sistema é o indireto, ou presidencialista. | E6: =IF(D6="","",IFERROR(INDEX(Temas!$C$2:$C$352,MATCH(D6,Temas!$A$2:$A$352,0)),"ID NÃO ENCONTRADO"))
A7: Q0026 | B7: Está fora do âmbito de proteção da Lei n.º 11.340/2006, que trata da violência doméstica contra a mulher, COMANDO: Assinale o que está fora do âmbito de proteção da Lei n.º 11.340/2006. | C7: A) a filha transexual que é ameaçada pelo pai dentro da própria\nresidência. B) a mãe vulnerável que é ameaçada e agredida pela própria\nfilha com a qual convive. C) a mulher agredida dentro do ambiente laboral por colega de\ntrabalho do sexo masculino com quem nunca teve relação\níntima ou de afeto. D) a empregada doméstica agredida pelo neto da empregadora\ndentro da casa desta. E) a mulher vítima de contravenção penal em razão do gênero. | E7: =IF(D7="","",IFERROR(INDEX(Temas!$C$2:$C$352,MATCH(D7,Temas!$A$2:$A$352,0)),"ID NÃO ENCONTRADO"))
A8: Q0031 | B8: Julgue o item a seguir, relativos a modelos teóricos da criminologia. De acordo com a teoria da anomia, o crime se origina da impossibilidade social do indivíduo de atingir suas metas pessoais, o que o faz negar a norma imposta e criar suas próprias regras, conforme o seu próprio interesse. COMANDO: Julgue o item a seguir. | C8: C) Certo E) Errado | E8: =IF(D8="","",IFERROR(INDEX(Temas!$C$2:$C$352,MATCH(D8,Temas!$A$2:$A$352,0)),"ID NÃO ENCONTRADO"))
A9: Q0034 | B9: A situação em que o habeas corpus é medida de impugnação cabível é COMANDO: Complete a frase sobre a situação em que o habeas corpus é medida de impugnação cabível. | C9: A) para trancar processo em curso por infração penal em que a pena pecuniária seja a única cominada. B) para que o advogado consiga ter acesso aos autos de inquérito policial. C) contra a decisão que inadmite assistente de acusação. D) para se pedir o desentranhamento de prova ilícita dos autos de inquérito policial ou de ação penal. E) para se obter restituição de coisas apreendidas. | E9: =IF(D9="","",IFERROR(INDEX(Temas!$C$2:$C$352,MATCH(D9,Temas!$A$2:$A$352,0)),"ID NÃO ENCONTRADO"))
A10: Q0040 | B10: Assinale a alternativa que traz duas características do recurso de apelação contra sentença condenatória do Tribunal do Júri que, cumuladas, podem levar à atribuição de efeito suspensivo ao referido recurso. | C10: A) Crime cometido sem violência ou grave ameaça e primariedade do apelante. B) Votação não unânime quanto a quesito essencial e excesso de prazo para formação da culpa. C) Pleitear reforma de sentença superior a 20 anos e levantar questão substancial, que pode resultar em anulação da sentença. D) Interposição por acusado primário e levantar questão substancial, que pode resultar em redução da pena para patamar inferior a 15 (quinze) anos de reclusão. E) Não ter propósito meramente protelatório e levantar questão substancial, que pode resultar em absolvição. | E10: =IF(D10="","",IFERROR(INDEX(Temas!$C$2:$C$352,MATCH(D10,Temas!$A$2:$A$352,0)),"ID NÃO ENCONTRADO"))
A11: Q0043 | B11: Sobre a fixação da pena, tem-se o seguinte: COMANDO: Complete o estudo sobre a fixação da pena. | C11: A) a existência de circunstância atenuante pode conduzir à redução da pena abaixo do mínimo legal. B) pelo critério trifásico, adotado pelo Código Penal, o juiz, na segunda fase, deverá apreciar as causas de aumento e de diminuição da parte geral e especial. C) o estabelecimento do valor de dias-multa independe da condição econômica do condenado. D) em caso de reincidência, fixada a pena em patamar inferior a 4 (quatro) anos, o condenado poderá iniciar o cumprimento da pena em regime semiaberto, desde que as circunstâncias judiciais o recomendem. | E11: =IF(D11="","",IFERROR(INDEX(Temas!$C$2:$C$352,MATCH(D11,Temas!$A$2:$A$352,0)),"ID NÃO ENCONTRADO"))
A12: Q0046 | B12: Acerca das nulidades processuais e dos vícios procedimentais, assinale a alternativa correta. COMANDO: Assinale a alternativa correta. | C12: A) As nulidades processuais penais sofrem influência da\ninstrumentalidade do processo, não se declarando\nqualquer tipo de nulidade se não verificado o prejuízo. B) Segundo a jurisprudência do Superior Tribunal de\nJustiça, a inversão da ordem das perguntas (art. 212,\nCPP) não gera nulidade, não implicando afronta ao\nprincípio do contraditório. C) As nulidades são divididas conforme a gravidade dos\nvícios, em relativas e absolutas, sendo a nulidade de ordem\nabsoluta reconhecida ainda que não haja prejuízo. D) A inépcia da acusação só pode ser apreciada na fase do\nartigo 396, do Código de Processo Penal, não podendo\ntal análise ser refeita na fase do artigo 397, do Código\nde Processo Penal, após a resposta à acusação. E) A coisa julgada sana todas as hipóteses de nulidades\nprocessuais penais. | E12: =IF(D12="","",IFERROR(INDEX(Temas!$C$2:$C$352,MATCH(D12,Temas!$A$2:$A$352,0)),"ID NÃO ENCONTRADO"))
A13: Q0047 | B13: Durante um pacífico protesto realizado no interior do Município Alfa, Caio, destoando do público presente e agindo com dolo, lançou uma pedra em direção ao pequeno estabelecimento comercial de João, gerando, em razão dos bens móveis destruídos, prejuízo considerável para a vítima. Na sequência, Caio jogou diversos paralelepípedos contra a sede da municipalidade, deteriorando o bem público. Nesse cenário, considerando as disposições do Código Penal, é correto afirmar que Caio responderá, em concurso, pelos crimes de COMANDO: Assinale a alternativa correta. | C13: A) \ndano qualificado em detrimento de João e dano qualificado\npor ter deteriorado bem público, hipóteses em que se procede\nmediante ação penal pública incondicionada. B) \ndano qualificado em detrimento de João, hipótese em que\nsomente se procede mediante representação do ofendido, e\ndano qualificado por ter deteriorado bem público. C) \ndano simples em detrimento de João e dano simples por ter\ndeteriorado bem público, hipóteses em que se procede\nmediante ação penal pública incondicionada. D) \ndano qualificado em detrimento de João, hipótese em que\nsomente se procede mediante queixa, e dano qualificado por\nter deteriorado bem público. E) \ndano simples em detrimento de João, hipótese em que\nsomente se procede mediante queixa, e dano qualificado por\nter deteriorado bem público. | E13: =IF(D13="","",IFERROR(INDEX(Temas!$C$2:$C$352,MATCH(D13,Temas!$A$2:$A$352,0)),"ID NÃO ENCONTRADO"))
... A71: Q0356 | B71: O concurso de crimes é o instituto que se verifica quando o agente, mediante uma ou várias condutas, pratica duas ou mais infrações penais. Com base nesse assunto, informe se é verdadeiro (V) ou falso (F) o que se afirma a seguir e assinale a alternativa com a sequência correta. ( ) O concurso material, também chamado de real, é aquele em que o agente, mediante uma única conduta, pratica dois ou mais crimes, idênticos ou não. ( ) No concurso material, há pluralidade de condutas e pluralidade de resultados. ( ) No que diz respeito ao concurso formal impróprio ou imperfeito, tal como no concurso material, serão somadas as penas de todos os crimes praticados pelo agente. ( ) De acordo com o Código Penal brasileiro, no concurso de crimes, as penas de multa são aplicadas distinta e integralmente para cada crime. | C71: A) V – F – V – F. B) F – V – F – V. C) V – V – F – V. D) F – V – V – V E) F – F – V – F. | E71: =IF(D71="","",IFERROR(INDEX(Temas!$C$2:$C$352,MATCH(D71,Temas!$A$2:$A$352,0)),"ID NÃO ENCONTRADO"))

Sheet Temas
A1: tema_id | B1: nível | C1: caminho | D1: pai_id
A2: 4366 | B2: 1 | C2: Criminologia > Classificação das Vítimas | D2: 4365
A3: 4367 | B3: 1 | C3: Criminologia > Classificação dos Criminosos | D3: 4365
A4: 4368 | B4: 1 | C4: Criminologia > Criminologia no Estado Democrático de Direito | D4: 4365
A5: 4370 | B5: 2 | C5: Criminologia > Criminologia no Estado Democrático de Direito > Modelos de Reação ao Delito | D5: 4368
A6: 4369 | B6: 2 | C6: Criminologia > Criminologia no Estado Democrático de Direito > Sistemas de Prevenção | D6: 4368
A7: 4371 | B7: 1 | C7: Criminologia > Etapas Evolutivas e Escolas Criminológicas | D7: 4365
A8: 4373 | B8: 2 | C8: Criminologia > Etapas Evolutivas e Escolas Criminológicas > Escolas Crimonológicas | D8: 4371
A9: 4372 | B9: 2 | C9: Criminologia > Etapas Evolutivas e Escolas Criminológicas > Etapas Evolutivas da Criminologia (Antiguidade, Idade Média e Idade Moderna) | D9: 4371
A10: 4374 | B10: 1 | C10: Criminologia > Política Criminal | D10: 4365
A11: 4375 | B11: 2 | C11: Criminologia > Política Criminal > Correntes da Política Criminal | D11: 4374
A12: 4376 | B12: 2 | C12: Criminologia > Política Criminal > Direito Penal do Inimigo | D12: 4374
A13: 4377 | B13: 1 | C13: Criminologia > Processos de Criminalização e Cifras Criminais | D13: 4365
... A352: 5592 | B352: 2 | C352: Processo Penal > Teoria Geral das Provas > Sistemas de Avaliação da Prova | D352: 5590
